benchmarks
tests
libtree
