Metadata-Version: 1.1
Name: libtree
Version: 6.0.1
Summary: Python Tree Library
Home-page: https://github.com/conceptsandtraining/libtree
Author: Fabian Kochem
Author-email: fabian.kochem@concepts-and-training.de
License: UNKNOWN
Platform: UNKNOWN
Classifier: Development Status :: 3 - Alpha
Classifier: Intended Audience :: Developers
Classifier: License :: OSI Approved :: MIT License
Classifier: Operating System :: OS Independent
Classifier: Programming Language :: Python
Classifier: Programming Language :: Python :: 2
Classifier: Programming Language :: Python :: 3
Classifier: Topic :: Database
Classifier: Topic :: Software Development :: Libraries
